birdwatcher/__init__.py
birdwatcher/_version.py
birdwatcher/backgroundsubtraction.py
birdwatcher/coordinatearrays.py
birdwatcher/ffmpeg.py
birdwatcher/frames.py
birdwatcher/plotting.py
birdwatcher/utils.py
birdwatcher/video.py
birdwatcher/movementdetection/__init__.py
birdwatcher/movementdetection/movementdetection.py
birdwatcher/movementdetection/parameterselection.py
birdwatcher/tests/__init__.py
birdwatcher/tests/test_backgroundsubtraction.py
birdwatcher/tests/test_coordinatearrays.py
birdwatcher/tests/test_frameprocessing.py
birdwatcher/tests/test_movementdetection.py
birdwatcher/tests/test_parameterselection.py
birdwatcher/tests/test_plotting.py
birdwatcher/tests/test_videoinput.py
birdwatcher/testvideos/zf20s_low.mp4
birdwatcher-0.5.0.dist-info/licenses/LICENSE
birdwatcher-0.5.0.dist-info/METADATA
birdwatcher-0.5.0.dist-info/WHEEL
birdwatcher-0.5.0.dist-info/top_level.txt
birdwatcher-0.5.0.dist-info/RECORD
