Metadata-Version: 2.4
Name: birdwatcher
Version: 0.5.0
Summary: A Python computer vision library for animal behavior
Author-email: Gabriel Beckers <g.j.l.beckers@uu.nl>, Carien Mol <c.mol@uu.nl>
License-Expression: BSD-3-Clause
Project-URL: Homepage, https://github.com/gbeckers/Birdwatcher
Project-URL: Repository, https://github.com/gbeckers/Birdwatcher.git
Project-URL: Documentation, https://birdwatcher.readthedocs.io/en/latest/
Keywords: animal,behavior,computer-vision,data-science,ffmpeg,opencv
Classifier: Programming Language :: Python :: 3
Classifier: Operating System :: OS Independent
Classifier: Development Status :: 4 - Beta
Classifier: Intended Audience :: Education
Classifier: Intended Audience :: Developers
Classifier: Intended Audience :: Information Technology
Classifier: Intended Audience :: Science/Research
License-File: LICENSE
Requires-Dist: darr==0.6.0
Requires-Dist: numpy==2.0.2
Requires-Dist: matplotlib==3.9.2
Requires-Dist: opencv-python==4.10.0.84
Requires-Dist: opencv-contrib-python==4.10.0.84
Requires-Dist: pandas==2.2.3
Requires-Dist: seaborn==0.13.2
Dynamic: license-file
